Metadata-Version: 2.1
Name: AgentlyCmd
Version: 0.0.0.2
Summary: Agently Shell Command.
Home-page: https://github.com/Maplemx/Agently
Author: Maplemx
Author-email: maplemx@gmail.com
License: Apache License, Version 2.0
Classifier: Programming Language :: Python :: 3
Classifier: License :: OSI Approved :: MIT License
Classifier: Operating System :: OS Independent
Requires-Python: >=3.8
